LICENSE.md
README.md
pyproject.toml
setup.py
pktree/__init__.py
pktree/hello.c
pktree/hello.pyx
pktree.egg-info/PKG-INFO
pktree.egg-info/SOURCES.txt
pktree.egg-info/dependency_links.txt
pktree.egg-info/requires.txt
pktree.egg-info/top_level.txt
pktree/ensemble/__init__.py
pktree/ensemble/_bagging.py
pktree/ensemble/_base.py
pktree/ensemble/_forest.py
pktree/ensemble/_gb.py
pktree/ensemble/_gradient_boosting.c
pktree/ensemble/_gradient_boosting.pyx
pktree/ensemble/_iforest.py
pktree/ensemble/_stacking.py
pktree/ensemble/_voting.py
pktree/ensemble/_weight_boosting.py
pktree/ensemble/_hist_gradient_boosting/__init__.py
pktree/ensemble/_hist_gradient_boosting/_binning.c
pktree/ensemble/_hist_gradient_boosting/_binning.pyx
pktree/ensemble/_hist_gradient_boosting/_bitset.c
pktree/ensemble/_hist_gradient_boosting/_bitset.pxd
pktree/ensemble/_hist_gradient_boosting/_bitset.pyx
pktree/ensemble/_hist_gradient_boosting/_gradient_boosting.c
pktree/ensemble/_hist_gradient_boosting/_gradient_boosting.pyx
pktree/ensemble/_hist_gradient_boosting/_predictor.c
pktree/ensemble/_hist_gradient_boosting/_predictor.pyx
pktree/ensemble/_hist_gradient_boosting/binning.py
pktree/ensemble/_hist_gradient_boosting/common.c
pktree/ensemble/_hist_gradient_boosting/common.pxd
pktree/ensemble/_hist_gradient_boosting/common.pyx
pktree/ensemble/_hist_gradient_boosting/gradient_boosting.py
pktree/ensemble/_hist_gradient_boosting/grower.py
pktree/ensemble/_hist_gradient_boosting/histogram.c
pktree/ensemble/_hist_gradient_boosting/histogram.pyx
pktree/ensemble/_hist_gradient_boosting/predictor.py
pktree/ensemble/_hist_gradient_boosting/splitting.c
pktree/ensemble/_hist_gradient_boosting/splitting.pyx
pktree/ensemble/_hist_gradient_boosting/utils.py
pktree/tree/__init__.py
pktree/tree/_classes.py
pktree/tree/_criterion.c
pktree/tree/_criterion.pxd
pktree/tree/_criterion.pyx
pktree/tree/_export.py
pktree/tree/_partitioner.c
pktree/tree/_partitioner.pxd
pktree/tree/_partitioner.pyx
pktree/tree/_reingold_tilford.py
pktree/tree/_splitter.c
pktree/tree/_splitter.pxd
pktree/tree/_splitter.pyx
pktree/tree/_tree.cpp
pktree/tree/_tree.pxd
