Metadata-Version: 2.2
Name: pktree
Version: 1.0.0
Summary: A Python package for incorporating biological prior knowledge into tree-based models
Author: Sofia Mongardi, Manuel Tacca, Marco Masseroli, Francesco Invernici
License: LICENSE.md
Project-URL: Homepage, https://github.com/SofSof98/pktree
Project-URL: Issues, https://github.com/SofSof98/pktree/issues
Classifier: Programming Language :: Python :: 3
Classifier: Programming Language :: Python :: 3.9
Classifier: Programming Language :: Cython
Classifier: Development Status :: 5 - Production/Stable
Classifier: Intended Audience :: Science/Research
Classifier: Topic :: Scientific/Engineering :: Bio-Informatics
Classifier: Topic :: Scientific/Engineering
Requires-Python: >=3.9
License-File: LICENSE.md
Requires-Dist: Cython>=3.0.10
Requires-Dist: numpy>=1.19.5
Requires-Dist: scipy>=1.6.0
Requires-Dist: joblib>=1.2.0
Requires-Dist: threadpoolctl>=3.1.0
Requires-Dist: scikit-learn
